[{"Dataset": "EN_NEW", "Dataset Size": 10000, "Model": "NMF", "Scores": {"npmi": 0.018633754353235728, "diversity": 0.57}, "Computation Time": 5.215447664260864, "Topics": [["plants", "tree", "oil", "flowers", "also", "used", "fragrance", "garden", "sweet", "rose"], ["beautiful", "small", "heart", "beauty", "one", "many", "eyes", "green", "sweet", "filled"], ["smell", "may", "life", "one", "sense", "flower", "made", "also", "taste", "however"], ["leaves", "flowers", "scent", "white", "long", "fragrant", "flower", "tree", "also", "large"], ["flowers", "sweet", "scent", "birds", "room", "would", "fragrance", "filled", "air", "may"], ["flower", "water", "scent", "oil", "air", "pleasant", "night", "well", "fragrance", "morning"], ["flowers", "plant", "smell", "small", "water", "strong", "taste", "white", "leaves", "many"], ["fragrant", "trees", "flowers", "beautiful", "filled", "along", "adorned", "many", "made", "covered"], ["one", "air", "every", "flowers", "time", "could", "see", "long", "among", "night"], ["love", "would", "flowers", "may", "man", "light", "fragrant", "around", "heart", "leaves"]]}, {"Dataset": "EN_NEW", "Dataset Size": 10000, "Model": "NMF", "Scores": {"npmi": 0.03387120971399599, "diversity": 0.545}, "Computation Time": 5.913973331451416, "Topics": [["flower", "two", "large", "filled", "air", "four", "leaves", "white", "open", "branches"], ["sweet", "flower", "many", "around", "smelling", "every", "perfume", "evening", "scented", "night"], ["flowers", "beautiful", "people", "scents", "sweet", "gardens", "large", "color", "along", "smelling"], ["water", "oil", "essential", "oils", "plant", "distilled", "distillation", "perfume", "amount", "aromatic"], ["tree", "leaves", "branches", "fruit", "white", "bark", "green", "yellow", "flowers", "wood"], ["flowers", "plant", "used", "leaves", "smell", "taste", "also", "bitter", "aromatic", "strong"], ["long", "fragrant", "small", "leaves", "flowers", "white", "inches", "green", "many", "large"], ["may", "smell", "color", "small", "strong", "often", "cats", "known", "scent", "odor"], ["one", "beautiful", "could", "see", "young", "day", "way", "among", "green", "make"], ["flowers", "fragrant", "fragrance", "garden", "beauty", "white", "beautiful", "blue", "colors", "old"], ["life", "rose", "white", "nature", "love", "also", "acid", "eyes", "sea", "heart"], ["smell", "flower", "garden", "sense", "scents", "animals", "plants", "odors", "also", "could"], ["flowers", "plants", "night", "love", "may", "fragrance", "insects", "could", "around", "see"], ["trees", "flowers", "many", "large", "every", "along", "various", "among", "place", "without"], ["god", "scent", "two", "made", "fragrance", "flowers", "small", "air", "white", "cream"], ["air", "flowers", "birds", "filled", "summer", "trees", "day", "sun", "singing", "sky"], ["scent", "flowers", "one", "flower", "also", "room", "another", "however", "oil", "strong"], ["fragrant", "nature", "plants", "flowers", "fruits", "sweet", "herbs", "earth", "various", "fields"], ["would", "filled", "flowers", "earth", "sky", "still", "place", "water", "day", "garden"], ["love", "god", "man", "heart", "beauty", "life", "soul", "joy", "one", "world"]]}, {"Dataset": "EN_NEW", "Dataset Size": 10000, "Model": "NMF", "Scores": {"npmi": 0.014290583357391282, "diversity": 0.5166666666666667}, "Computation Time": 7.3538055419921875, "Topics": [["love", "flower", "perfumes", "scents", "around", "god", "king", "time", "long", "incense"], ["oil", "water", "flowers", "used", "essential", "oils", "sweet", "also", "scented", "trees"], ["small", "flowers", "many", "one", "long", "five", "smelling", "seeds", "white", "middle"], ["leaves", "two", "white", "flowers", "inches", "three", "fragrant", "smooth", "feet", "stem"], ["would", "garden", "could", "flowers", "place", "time", "beauty", "often", "day", "away"], ["flowers", "scent", "colors", "time", "blue", "scents", "white", "box", "however", "summer"], ["one", "flowers", "god", "king", "beautiful", "upon", "day", "sun", "scents", "another"], ["light", "sun", "night", "every", "sky", "birds", "gentle", "morning", "sweet", "earth"], ["cats", "wild", "without", "old", "life", "known", "days", "different", "scents", "regions"], ["flowers", "flower", "large", "insects", "color", "petals", "four", "pollen", "colored", "bloom"], ["trees", "filled", "large", "beautiful", "covered", "birds", "around", "along", "flowers", "house"], ["sweet", "air", "smelling", "beautiful", "rose", "scented", "cream", "music", "perfume", "filled"], ["also", "flowers", "aromatic", "plants", "taste", "used", "known", "found", "strong", "smell"], ["plant", "leaves", "seeds", "pleasant", "grows", "stems", "known", "species", "grow", "native"], ["plants", "perfumes", "various", "scents", "odors", "animals", "sweet", "however", "different", "fruits"], ["long", "fragrance", "roses", "two", "sweet", "white", "shaped", "fruit", "day", "blossoms"], ["flower", "smell", "water", "hand", "sense", "beauty", "perfume", "without", "never", "powder"], ["love", "fragrance", "flowers", "garden", "heart", "light", "strong", "scent", "beauty", "room"], ["life", "nature", "one", "heart", "man", "see", "soul", "beauty", "time", "come"], ["earth", "acid", "common", "black", "white", "could", "smooth", "eyes", "grass", "long"], ["made", "well", "water", "let", "fragrant", "night", "body", "make", "white", "though"], ["air", "room", "fresh", "pleasant", "flowers", "open", "filled", "effects", "water", "space"], ["fragrant", "flowers", "shrubs", "garden", "beautiful", "adorned", "often", "old", "plants", "large"], ["may", "could", "around", "people", "man", "fragrant", "many", "without", "day", "time"], ["scent", "rose", "found", "place", "beautiful", "could", "green", "filled", "small", "breeze"], ["leaves", "tree", "also", "white", "may", "large", "known", "branches", "similar", "bark"], ["flowers", "beautiful", "fragrance", "delightful", "many", "plants", "tree", "leaves", "well", "around"], ["smell", "sense", "taste", "pleasant", "flowers", "god", "heart", "every", "always", "eyes"], ["room", "one", "said", "filled", "would", "young", "little", "woman", "women", "way"], ["tree", "used", "smell", "flowers", "color", "fruit", "leaves", "strong", "taste", "yellow"]]}, {"Dataset": "EN_NEW", "Dataset Size": 10000, "Model": "NMF", "Scores": {"npmi": 0.00012833350660180972, "diversity": 0.48}, "Computation Time": 7.702301025390625, "Topics": [["cats", "tree", "nature", "wild", "used", "known", "beauty", "wood", "fragrance", "make"], ["long", "white", "small", "leaves", "five", "shaped", "smooth", "green", "two", "color"], ["air", "room", "sweet", "filled", "life", "eyes", "white", "house", "common", "fragrance"], ["scent", "flowers", "strong", "also", "box", "similar", "painted", "open", "found", "window"], ["would", "filled", "see", "man", "could", "air", "scents", "white", "flowers", "around"], ["animals", "air", "odors", "every", "flower", "animal", "different", "scents", "scent", "plant"], ["smell", "strong", "taste", "flowers", "found", "unpleasant", "many", "aromatic", "see", "bitter"], ["oil", "trees", "fragrant", "essential", "oils", "used", "small", "honey", "extract", "soap"], ["would", "one", "life", "water", "two", "young", "come", "among", "three", "adam"], ["fragrant", "flowers", "around", "flower", "shrubs", "often", "two", "king", "one", "beautiful"], ["flowers", "fragrant", "white", "plant", "used", "long", "highly", "fragrance", "blue", "scented"], ["two", "cases", "four", "feet", "flowers", "three", "inches", "fevers", "plant", "said"], ["large", "used", "known", "also", "aromatic", "well", "however", "believed", "found", "commonly"], ["leaves", "plant", "flowers", "branches", "green", "stem", "similar", "stems", "yellow", "bitter"], ["may", "rose", "love", "perfume", "cats", "river", "spirit", "hand", "wild", "time"], ["water", "scents", "flowers", "scented", "orange", "distilled", "distillation", "oil", "earth", "sweet"], ["smell", "sense", "however", "way", "humans", "nerves", "always", "odor", "olfactory", "long"], ["trees", "flowers", "filled", "light", "love", "fragrance", "lovely", "tall", "large", "orange"], ["taste", "bitter", "fruit", "small", "seeds", "perfumes", "aromatic", "one", "similar", "made"], ["felt", "could", "time", "world", "face", "would", "woman", "sea", "left", "moment"], ["green", "day", "flowers", "still", "found", "every", "small", "feet", "nectar", "insects"], ["flowers", "life", "time", "long", "beautiful", "earth", "heart", "sky", "nature", "bright"], ["old", "flowers", "roses", "well", "beauty", "man", "house", "scent", "young", "among"], ["plants", "flowers", "fragrance", "many", "flora", "region", "chief", "people", "flowering", "grass"], ["flowers", "oil", "well", "fragrance", "known", "flower", "could", "also", "scents", "air"], ["insects", "flowers", "various", "garden", "pleasant", "also", "often", "however", "others", "substances"], ["beautiful", "air", "fragrant", "god", "flowers", "trees", "filled", "birds", "spring", "covered"], ["plant", "common", "white", "large", "yellow", "color", "plants", "red", "purple", "every"], ["may", "one", "good", "never", "person", "honey", "god", "plant", "things", "insects"], ["one", "sweet", "also", "fragrant", "small", "many", "flowers", "made", "great", "known"], ["tree", "fruit", "flowers", "orange", "branches", "also", "yellow", "white", "sweet", "grows"], ["garden", "could", "fragrant", "place", "without", "flowers", "little", "house", "away", "first"], ["one", "flowers", "seen", "smell", "color", "time", "along", "red", "smelling", "green"], ["love", "heart", "eyes", "flower", "one", "man", "never", "beauty", "life", "see"], ["small", "many", "feet", "sometimes", "body", "side", "resembling", "plant", "could", "food"], ["perfumes", "also", "perfume", "king", "sweet", "smelling", "incense", "man", "made", "along"], ["night", "morning", "sun", "birds", "evening", "day", "dew", "gentle", "land", "fragrance"], ["cream", "powder", "fragrance", "perfume", "face", "soap", "bath", "skin", "beautiful", "hair"], ["flower", "acid", "scent", "violet", "plant", "rose", "color", "process", "sweet", "purple"], ["sweet", "love", "god", "flowers", "joy", "smelling", "soul", "songs", "scented", "light"]]}, {"Dataset": "EN_NEW", "Dataset Size": 10000, "Model": "NMF", "Scores": {"npmi": 0.010462726117345804, "diversity": 0.444}, "Computation Time": 9.02873420715332, "Topics": [["sweet", "night", "plants", "without", "herbs", "evening", "sun", "water", "first", "dew"], ["two", "made", "king", "one", "fragrant", "filled", "table", "room", "great", "adorned"], ["one", "flower", "long", "day", "well", "rose", "said", "perfume", "scent", "little"], ["flowers", "sweet", "fragrant", "insects", "scented", "color", "colors", "bees", "adorned", "fragrance"], ["tree", "one", "flowers", "large", "fruit", "beautiful", "fragrant", "plants", "fragrance", "bark"], ["trees", "tree", "sweet", "leaves", "branches", "fruit", "found", "orange", "small", "wild"], ["oil", "essential", "oils", "leaves", "time", "volatile", "flowers", "mixture", "extract", "small"], ["garden", "house", "smell", "many", "room", "open", "could", "scent", "body", "sense"], ["room", "flowers", "light", "among", "fragrance", "pleasant", "eyes", "one", "night", "much"], ["plants", "long", "leaves", "flowers", "many", "flora", "seeds", "chief", "grow", "region"], ["along", "also", "well", "city", "part", "substances", "aromatic", "river", "strong", "harmful"], ["powder", "cream", "perfume", "soap", "bath", "face", "hand", "skin", "hair", "water"], ["also", "flower", "two", "known", "flowers", "three", "however", "cases", "leaves", "root"], ["fragrant", "rose", "plants", "flowers", "various", "beautiful", "herbs", "highly", "perfumes", "using"], ["sweet", "beauty", "god", "time", "flowers", "early", "acid", "see", "fragrance", "air"], ["filled", "scents", "delightful", "pleasant", "beautiful", "around", "gardens", "shrubs", "air", "gentle"], ["god", "man", "love", "would", "earth", "without", "heaven", "face", "things", "sun"], ["cats", "wild", "different", "regions", "known", "often", "certain", "old", "tropical", "eat"], ["sweet", "flower", "old", "white", "scent", "fragrant", "house", "around", "feet", "felt"], ["every", "filled", "flowers", "felt", "joy", "back", "around", "air", "scent", "seemed"], ["smell", "taste", "sense", "strong", "unpleasant", "bitter", "flowers", "pleasant", "odor", "similar"], ["love", "eyes", "fragrance", "roses", "heart", "bright", "deep", "sweet", "white", "flowers"], ["used", "water", "made", "oil", "also", "flowers", "orange", "bitter", "oils", "aromatic"], ["flowers", "large", "leaves", "white", "long", "fragrant", "smooth", "shaped", "clusters", "stem"], ["flower", "fragrance", "beauty", "known", "scent", "god", "bloom", "color", "less", "used"], ["small", "many", "stalks", "five", "top", "round", "middle", "yellow", "heads", "somewhat"], ["one", "life", "time", "heart", "come", "god", "let", "soul", "good", "night"], ["trees", "may", "white", "roses", "rose", "green", "along", "cold", "spring", "beautiful"], ["would", "could", "flowers", "scent", "scents", "nature", "people", "trees", "lady", "perfumes"], ["place", "flowers", "fragrant", "time", "adam", "others", "old", "land", "many", "fruits"], ["scent", "flowers", "box", "painted", "time", "strong", "fragrance", "pink", "found", "honey"], ["often", "every", "life", "may", "morning", "gentle", "found", "however", "sing", "fragrance"], ["water", "flowers", "leaves", "rose", "scented", "one", "often", "earth", "hot", "river"], ["may", "would", "young", "heart", "come", "cases", "said", "whose", "man", "say"], ["love", "air", "scented", "trees", "people", "flowers", "gardens", "often", "felt", "fragrant"], ["may", "love", "insects", "animals", "odors", "man", "scents", "flower", "time", "animal"], ["life", "see", "love", "filled", "one", "could", "make", "air", "morning", "sky"], ["beauty", "nature", "birds", "upon", "heart", "earth", "joy", "around", "summer", "sun"], ["dark", "sun", "sky", "day", "fragrant", "among", "blue", "river", "sea", "yet"], ["life", "large", "women", "body", "felt", "flower", "surrounded", "found", "voice", "tree"], ["flowers", "scents", "made", "sense", "day", "well", "night", "many", "fragrant", "trees"], ["flowers", "smelling", "small", "open", "without", "often", "plant", "scent", "however", "strong"], ["could", "never", "flowers", "day", "away", "little", "see", "birds", "beautiful", "seen"], ["plant", "flowers", "leaves", "bitter", "aromatic", "strong", "taste", "pleasant", "properties", "smell"], ["leaves", "green", "white", "yellow", "two", "calyx", "short", "pale", "oblong", "five"], ["beautiful", "light", "colors", "man", "sun", "world", "spring", "every", "summer", "flowers"], ["color", "long", "plant", "feet", "branches", "around", "two", "three", "four", "red"], ["air", "scent", "nature", "music", "effects", "sky", "heat", "fresh", "space", "sun"], ["common", "sweet", "wood", "rose", "tree", "black", "lavender", "aromatic", "roses", "leaved"], ["perfumes", "various", "king", "one", "people", "also", "new", "certain", "oil", "well"]]}]